<Properties>
  <MonoDevelop.Ide.Workbench ActiveDocument="NewMonoProject/MyClass.cs">
    <Files>
      <File FileName="NewMonoProject/MyClass.cs" Line="8" Column="14" />
    </Files>
    <Pads>
      <Pad Id="ProjectPad">
        <State name="__root__">
          <Node name="NewMonoProject" expanded="True">
            <Node name="NewMonoProject" expanded="True">
              <Node name="MyClass.cs" selected="True" />
            </Node>
          </Node>
        </State>
      </Pad>
    </Pads>
  </MonoDevelop.Ide.Workbench>
  <MonoDevelop.Ide.DebuggingService.PinnedWatches />
  <MonoDevelop.Ide.Workspace />
  <MonoDevelop.Ide.ItemProperties.NewMonoProject FirstBuild="True" />
  <MonoDevelop.Ide.DebuggingService.Breakpoints>
    <BreakpointStore />
  </MonoDevelop.Ide.DebuggingService.Breakpoints>
  <MultiItemStartupConfigurations />
</Properties>